{"cameraMode":{"drawMode":0,"name":"Shaded","section":"Shading Mode"},"sceneLighting":true,"audioPlay":false,"sceneViewState":{"m_AlwaysRefresh":false,"showFog":true,"showSkybox":true,"showFlares":true,"showImageEffects":true,"showParticleSystems":true,"showVisualEffectGraphs":true,"m_FxEnabled":true},"in2DMode":false,"pivot":{"x":-17.718780517578126,"y":-61.27611541748047,"z":28.906036376953126},"rotation":{"x":-0.42818188667297366,"y":-0.011982777155935765,"z":0.005768183618783951,"w":-0.9036510586738586},"size":48.59064483642578,"orthographic":false}